here_transit/__init__.py
here_transit/exceptions.py
here_transit/here_transit.py
here_transit/model.py
here_transit-1.2.0.dist-info/METADATA
here_transit-1.2.0.dist-info/WHEEL
here_transit-1.2.0.dist-info/LICENSE
here_transit-1.2.0.dist-info/RECORD
