Metadata-Version: 2.1
Name: here-transit
Version: 1.2.0
Summary: Asynchronous Python client for the HERE Transit V8 API
Home-page: http://github.com/eifinger/here_transit
License: MIT
Keywords: aiohttp,asyncio,here,here-api,routing,transit
Author: Kevin Stillhammer
Author-email: kevin.stillhammer@gmail.com
Requires-Python: >=3.8,<4.0
Classifier: Intended Audience :: Developers
Classifier: License :: OSI Approved :: MIT License
Classifier: Operating System :: OS Independent
Classifier: Programming Language :: Python
Classifier: Programming Language :: Python :: 3
Classifier: Programming Language :: Python :: 3.8
Classifier: Programming Language :: Python :: 3.9
Classifier: Programming Language :: Python :: 3.10
Classifier: Programming Language :: Python :: 3.11
Classifier: Programming Language :: Python :: 3
Classifier: Topic :: Software Development :: Libraries :: Python Modules
Requires-Dist: aiohttp (>=3.8.1,<4.0.0)
Requires-Dist: async-timeout (>=4.0.2,<5.0.0)
Requires-Dist: yarl (>=1.7.2,<2.0.0)
Project-URL: Repository, http://github.com/eifinger/here_transit
